yamlsettings/__init__.py
yamlsettings/helpers.py
yamlsettings/yamldict.py
yamlsettings/extensions/__init__.py
yamlsettings/extensions/base.py
yamlsettings/extensions/local.py
yamlsettings/extensions/package.py
yamlsettings/extensions/registry.py
yamlsettings-2.1.2.dist-info/LICENSE
yamlsettings-2.1.2.dist-info/METADATA
yamlsettings-2.1.2.dist-info/WHEEL
yamlsettings-2.1.2.dist-info/top_level.txt
yamlsettings-2.1.2.dist-info/RECORD
