Metadata-Version: 2.1
Name: yamlsettings
Version: 2.1.2
Summary: Yaml Settings Configuration Module
Home-page: https://github.com/KyleJamesWalker/yamlsettings
Author: Kyle James Walker
Author-email: KyleJamesWalker@gmail.com
License: MIT
Classifier: Development Status :: 5 - Production/Stable
Classifier: Intended Audience :: Developers
Classifier: License :: OSI Approved :: MIT License
Classifier: Natural Language :: English
Classifier: Programming Language :: Python :: 3.8
Classifier: Programming Language :: Python :: 3.9
Classifier: Programming Language :: Python :: 3.10
Classifier: Programming Language :: Python :: 3.11
Classifier: Programming Language :: Python :: 3.12
License-File: LICENSE
Requires-Dist: PyYAML >=5
Requires-Dist: six
Provides-Extra: all
Requires-Dist: PyYAML >=5 ; extra == 'all'
Requires-Dist: mock ; extra == 'all'
Requires-Dist: nose ; extra == 'all'
Requires-Dist: pytest ; extra == 'all'
Requires-Dist: pytest-mock ; extra == 'all'
Requires-Dist: pytest-runner ; extra == 'all'
Requires-Dist: six ; extra == 'all'
Provides-Extra: package
Requires-Dist: PyYAML >=5 ; extra == 'package'
Requires-Dist: six ; extra == 'package'
Provides-Extra: setup
Requires-Dist: pytest-runner ; extra == 'setup'
Provides-Extra: test
Requires-Dist: nose ; extra == 'test'
Requires-Dist: mock ; extra == 'test'
Requires-Dist: pytest ; extra == 'test'
Requires-Dist: pytest-mock ; extra == 'test'
